setup.py
src/usls.py
src/useless/__init__.py
src/useless/PE/__init__.py
src/useless/PE/datatypes.py
src/useless/PE/enums.py
src/useless/PE/structures.py
src/useless/common/__init__.py
src/useless/common/datatypes.py
src/useless/common/enums.py
src/useless/common/structures.py
src/useless/display/PE.py
src/useless/display/__init__.py
src/useless/display/elf.py
src/useless/elf/__init__.py
src/useless/elf/datatypes.py
src/useless/elf/enums.py
src/useless/elf/structures.py
src/useless/identify/__init__.py
useless.egg-info/PKG-INFO
useless.egg-info/SOURCES.txt
useless.egg-info/dependency_links.txt
useless.egg-info/requires.txt
useless.egg-info/top_level.txt