Metadata-Version: 1.0
Name: useless
Version: 0.5
Summary: Useless is useless. Oh yeah, and parses bit and piecesof ELF and PE dynamic libraries
Home-page: https://github.com/riccardocagnasso/python-opendb/blob/master/setup.py
Author: Riccardo Cagnasso
Author-email: riccardo@phascode.org
License: MIT
Platform: UNKNOWN
